hail_scripts/__init__.py
hail_scripts/computed_fields/__init__.py
hail_scripts/computed_fields/flags.py
hail_scripts/computed_fields/test_flags.py
hail_scripts/computed_fields/test_variant_id.py
hail_scripts/computed_fields/variant_id.py
hail_scripts/computed_fields/vep.py
hail_scripts/elasticsearch/__init__.py
hail_scripts/elasticsearch/elasticsearch_client_v7.py
hail_scripts/elasticsearch/elasticsearch_client_v8.py
hail_scripts/elasticsearch/elasticsearch_utils.py
hail_scripts/elasticsearch/elasticsearch_utils_tests.py
hail_scripts/elasticsearch/hail_elasticsearch_client.py
hail_scripts/update_models/__init__.py
hail_scripts/update_models/update_mt_schema.py
hail_scripts/utils/__init__.py
hail_scripts/utils/clinvar.py
hail_scripts/utils/hail_utils.py
lib/__init__.py
lib/global_config.py
lib/hail_tasks.py
lib/hail_vep_runners.py
lib/model/__init__.py
lib/model/base_mt_schema.py
lib/model/seqr_mt_schema.py
seqr_loader-1.2.5.dist-info/LICENSE
seqr_loader-1.2.5.dist-info/METADATA
seqr_loader-1.2.5.dist-info/WHEEL
seqr_loader-1.2.5.dist-info/top_level.txt
seqr_loader-1.2.5.dist-info/RECORD
